crland/__init__.py
crland/agent/__init__.py
crland/agent/base.py
crland/agent/callback.py
crland/agent/collect/__init__.py
crland/agent/collect/base.py
crland/agent/collect/prompt.py
crland/agent/rank/__init__.py
crland/agent/rank/base.py
crland/agent/rank/output_parser.py
crland/agent/rank/prompt.py
crland/agent/recall/__init__.py
crland/agent/recall/base.py
crland/config/__init__.py
crland/config/config.py
crland/datacenter/__init__.py
crland/datacenter/database/__init__.py
crland/datacenter/database/base.py
crland/datacenter/echarts/__init__.py
crland/datacenter/echarts/bar.py
crland/datacenter/echarts/base.py
crland/datacenter/echarts/stacked_line.py
crland/datacenter/knowledge/__init__.py
crland/datacenter/knowledge/executor.py
crland/datacenter/knowledge/factor.py
crland/datacenter/knowledge/graph.py
crland/datacenter/knowledge/wrapper.py
crland/models/__init__.py
crland/models/base.py
crland/models/guanaco.py
crland/searchhub/__init__.py
crland/searchhub/page_manage/__init__.py
crland/searchhub/page_manage/base.py
crland/searchhub/page_manage/company.py
crland/searchhub/page_manage/factor.py
crland/searchhub/page_manage/model.py
crland/searchhub/page_manage/role.py
crland/searchhub/page_manage/user.py
crland/searchhub/recall/__init__.py
crland/searchhub/recall/base.py
crland/searchhub/recall/parser.py
crland/searchhub/recall/channel/__init__.py
crland/searchhub/recall/channel/es.py
crland/searchhub/recall/channel/faiss.py
crland/searchhub/task/__init__.py
crland/searchhub/task/base.py
crland/searchhub/task/task_manager.py
crland/searchhub/task/analysis/__init__.py
crland/searchhub/task/analysis/analysis_task.py
crland/searchhub/task/search/__init__.py
crland/searchhub/task/search/search_task.py
crland/tools/__init__.py
crland/tools/log.py
crland/tools/singleton.py
crland/tools/embeddings/__init__.py
crland/tools/embeddings/base.py
crland/tools/embeddings/embedding_manager.py
crland/tools/embeddings/huggingface_embedding.py
crland-0.3.dist-info/LICENSE
crland-0.3.dist-info/METADATA
crland-0.3.dist-info/WHEEL
crland-0.3.dist-info/top_level.txt
crland-0.3.dist-info/RECORD
