Metadata-Version: 2.1
Name: crland
Version: 0.3
Summary: llm agent framework
Home-page: 
Author: Bin ZHU
Author-email: 
License: UNKNOWN
Platform: UNKNOWN
Classifier: Programming Language :: Python :: 3
Classifier: License :: OSI Approved :: MIT License
Classifier: Operating System :: OS Independent
License-File: LICENSE
Requires-Dist: langchain (==0.0.266)
Requires-Dist: py-mini-racer (==0.6.0)
